{
  "version": "overlay.v1",
  "generated_at_utc": "2025-10-17T03:33:23.917981Z",
  "items": [
    {
      "name": "Hercules",
      "center": {
        "latitude": 31.565603286497865,
        "longitude": -179.4028817814264
      },
      "radiusMeters": 600000.0,
      "icrs": {
        "ra_deg": 259.845,
        "dec_deg": 31.566
      },
      "meta": {
        "visibilityTonight": {
          "visible": true,
          "max_alt_deg": 90.0,
          "max_alt_time_utc": "2025-10-17T03:33:23.917981Z",
          "zenith_sep_deg": 0.0,
          "hours_local": []
        }
      }
    },
    {
      "name": "Ara",
      "center": {
        "latitude": -55.16142525156105,
        "longitude": -176.01876629151184
      },
      "radiusMeters": 600000.0,
      "icrs": {
        "ra_deg": 263.229,
        "dec_deg": -55.161
      },
      "meta": {
        "visibilityTonight": {
          "visible": true,
          "max_alt_deg": 90.0,
          "max_alt_time_utc": "2025-10-17T03:33:23.917981Z",
          "zenith_sep_deg": 0.0,
          "hours_local": []
        }
      }
    },
    {
      "name": "Corona Australis",
      "center": {
        "latitude": -40.183741399627394,
        "longitude": -159.2477627816465
      },
      "radiusMeters": 600000.0,
      "icrs": {
        "ra_deg": 280.0,
        "dec_deg": -40.184
      },
      "meta": {
        "visibilityTonight": {
          "visible": true,
          "max_alt_deg": 90.0,
          "max_alt_time_utc": "2025-10-17T03:33:23.917981Z",
          "zenith_sep_deg": 0.0,
          "hours_local": []
        }
      }
    },
    {
      "name": "Scutum",
      "center": {
        "latitude": -8.0,
        "longitude": -159.2477627816465
      },
      "radiusMeters": 600000.0,
      "icrs": {
        "ra_deg": 280.0,
        "dec_deg": -8.0
      },
      "meta": {
        "visibilityTonight": {
          "visible": true,
          "max_alt_deg": 90.0,
          "max_alt_time_utc": "2025-10-17T03:33:23.917981Z",
          "zenith_sep_deg": 0.0,
          "hours_local": []
        }
      }
    },
    {
      "name": "Lyra",
      "center": {
        "latitude": 36.066475262469574,
        "longitude": -155.24776278164654
      },
      "radiusMeters": 600000.0,
      "icrs": {
        "ra_deg": 284.0,
        "dec_deg": 36.066
      },
      "meta": {
        "visibilityTonight": {
          "visible": true,
          "max_alt_deg": 90.0,
          "max_alt_time_utc": "2025-10-17T03:33:23.917981Z",
          "zenith_sep_deg": 0.0,
          "hours_local": []
        }
      }
    },
    {
      "name": "Sagittarius",
      "center": {
        "latitude": -27.063089394805285,
        "longitude": -152.1218789393248
      },
      "radiusMeters": 600000.0,
      "icrs": {
        "ra_deg": 287.126,
        "dec_deg": -27.063
      },
      "meta": {
        "visibilityTonight": {
          "visible": true,
          "max_alt_deg": 90.0,
          "max_alt_time_utc": "2025-10-17T03:33:23.917981Z",
          "zenith_sep_deg": 0.0,
          "hours_local": []
        }
      }
    },
    {
      "name": "Telescopium",
      "center": {
        "latitude": -52.33912781052116,
        "longitude": -147.24776278164654
      },
      "radiusMeters": 600000.0,
      "icrs": {
        "ra_deg": 292.0,
        "dec_deg": -52.339
      },
      "meta": {
        "visibilityTonight": {
          "visible": true,
          "max_alt_deg": 90.0,
          "max_alt_time_utc": "2025-10-17T03:33:23.917981Z",
          "zenith_sep_deg": 0.0,
          "hours_local": []
        }
      }
    },
    {
      "name": "Aquila",
      "center": {
        "latitude": 2.9227174145353323,
        "longitude": -143.9576735026876
      },
      "radiusMeters": 600000.0,
      "icrs": {
        "ra_deg": 295.29,
        "dec_deg": 2.923
      },
      "meta": {
        "visibilityTonight": {
          "visible": true,
          "max_alt_deg": 90.0,
          "max_alt_time_utc": "2025-10-17T03:33:23.917981Z",
          "zenith_sep_deg": 0.0,
          "hours_local": []
        }
      }
    },
    {
      "name": "Pavo",
      "center": {
        "latitude": -68.40374312508712,
        "longitude": -141.73130427451417
      },
      "radiusMeters": 600000.0,
      "icrs": {
        "ra_deg": 297.516,
        "dec_deg": -68.404
      },
      "meta": {
        "visibilityTonight": {
          "visible": true,
          "max_alt_deg": 90.0,
          "max_alt_time_utc": "2025-10-17T03:33:23.917981Z",
          "zenith_sep_deg": 0.0,
          "hours_local": []
        }
      }
    },
    {
      "name": "Vulpecula",
      "center": {
        "latitude": 24.419544549806655,
        "longitude": -135.24776278164654
      },
      "radiusMeters": 600000.0,
      "icrs": {
        "ra_deg": 304.0,
        "dec_deg": 24.42
      },
      "meta": {
        "visibilityTonight": {
          "visible": true,
          "max_alt_deg": 90.0,
          "max_alt_time_utc": "2025-10-17T03:33:23.917981Z",
          "zenith_sep_deg": 0.0,
          "hours_local": []
        }
      }
    },
    {
      "name": "Cygnus",
      "center": {
        "latitude": 43.40938132705002,
        "longitude": -130.74255184653305
      },
      "radiusMeters": 600000.0,
      "icrs": {
        "ra_deg": 308.505,
        "dec_deg": 43.409
      },
      "meta": {
        "visibilityTonight": {
          "visible": true,
          "max_alt_deg": 90.0,
          "max_alt_time_utc": "2025-10-17T03:33:23.917981Z",
          "zenith_sep_deg": 0.0,
          "hours_local": []
        }
      }
    },
    {
      "name": "Delphinus",
      "center": {
        "latitude": 13.363017802902018,
        "longitude": -129.8859169434337
      },
      "radiusMeters": 600000.0,
      "icrs": {
        "ra_deg": 309.362,
        "dec_deg": 13.363
      },
      "meta": {
        "visibilityTonight": {
          "visible": true,
          "max_alt_deg": 90.0,
          "max_alt_time_utc": "2025-10-17T03:33:23.917981Z",
          "zenith_sep_deg": 0.0,
          "hours_local": []
        }
      }
    },
    {
      "name": "Microscopium",
      "center": {
        "latitude": -36.066475262469574,
        "longitude": -123.24776278164654
      },
      "radiusMeters": 600000.0,
      "icrs": {
        "ra_deg": 316.0,
        "dec_deg": -36.066
      },
      "meta": {
        "visibilityTonight": {
          "visible": true,
          "max_alt_deg": 90.0,
          "max_alt_time_utc": "2025-10-17T03:33:23.917981Z",
          "zenith_sep_deg": 0.0,
          "hours_local": []
        }
      }
    },
    {
      "name": "Capricornus",
      "center": {
        "latitude": -20.22605193029682,
        "longitude": -123.24776278164654
      },
      "radiusMeters": 600000.0,
      "icrs": {
        "ra_deg": 316.0,
        "dec_deg": -20.226
      },
      "meta": {
        "visibilityTonight": {
          "visible": true,
          "max_alt_deg": 90.0,
          "max_alt_time_utc": "2025-10-17T03:33:23.917981Z",
          "zenith_sep_deg": 0.0,
          "hours_local": []
        }
      }
    },
    {
      "name": "Equuleus",
      "center": {
        "latitude": 8.0,
        "longitude": -119.24776278164654
      },
      "radiusMeters": 600000.0,
      "icrs": {
        "ra_deg": 320.0,
        "dec_deg": 8.0
      },
      "meta": {
        "visibilityTonight": {
          "visible": true,
          "max_alt_deg": 90.0,
          "max_alt_time_utc": "2025-10-17T03:33:23.917981Z",
          "zenith_sep_deg": 0.0,
          "hours_local": []
        }
      }
    },
    {
      "name": "Indus",
      "center": {
        "latitude": -60.7659030742713,
        "longitude": -116.30778232542883
      },
      "radiusMeters": 600000.0,
      "icrs": {
        "ra_deg": 322.94,
        "dec_deg": -60.766
      },
      "meta": {
        "visibilityTonight": {
          "visible": true,
          "max_alt_deg": 90.0,
          "max_alt_time_utc": "2025-10-17T03:33:23.917981Z",
          "zenith_sep_deg": 0.0,
          "hours_local": []
        }
      }
    },
    {
      "name": "Octans",
      "center": {
        "latitude": -81.0289837998777,
        "longitude": -115.81772673575972
      },
      "radiusMeters": 600000.0,
      "icrs": {
        "ra_deg": 323.43,
        "dec_deg": -81.029
      },
      "meta": {
        "visibilityTonight": {
          "visible": true,
          "max_alt_deg": 90.0,
          "max_alt_time_utc": "2025-10-17T03:33:23.917981Z",
          "zenith_sep_deg": 0.0,
          "hours_local": []
        }
      }
    },
    {
      "name": "Aquarius",
      "center": {
        "latitude": -10.760783663282659,
        "longitude": -104.93544546692226
      },
      "radiusMeters": 600000.0,
      "icrs": {
        "ra_deg": 334.312,
        "dec_deg": -10.761
      },
      "meta": {
        "visibilityTonight": {
          "visible": true,
          "max_alt_deg": 90.0,
          "max_alt_time_utc": "2025-10-17T03:33:23.917981Z",
          "zenith_sep_deg": 0.0,
          "hours_local": []
        }
      }
    },
    {
      "name": "Pisces Austrinus",
      "center": {
        "latitude": -32.16783809218905,
        "longitude": -103.24776278164654
      },
      "radiusMeters": 600000.0,
      "icrs": {
        "ra_deg": 336.0,
        "dec_deg": -32.168
      },
      "meta": {
        "visibilityTonight": {
          "visible": true,
          "max_alt_deg": 90.0,
          "max_alt_time_utc": "2025-10-17T03:33:23.917981Z",
          "zenith_sep_deg": 0.0,
          "hours_local": []
        }
      }
    },
    {
      "name": "Grus",
      "center": {
        "latitude": -47.1706329718894,
        "longitude": -102.42062557673961
      },
      "radiusMeters": 600000.0,
      "icrs": {
        "ra_deg": 336.827,
        "dec_deg": -47.171
      },
      "meta": {
        "visibilityTonight": {
          "visible": true,
          "max_alt_deg": 90.0,
          "max_alt_time_utc": "2025-10-17T03:33:23.917981Z",
          "zenith_sep_deg": 0.0,
          "hours_local": []
        }
      }
    },
    {
      "name": "Cepheus",
      "center": {
        "latitude": 74.5204779148747,
        "longitude": -100.36308992731557
      },
      "radiusMeters": 600000.0,
      "icrs": {
        "ra_deg": 338.885,
        "dec_deg": 74.52
      },
      "meta": {
        "visibilityTonight": {
          "visible": true,
          "max_alt_deg": 90.0,
          "max_alt_time_utc": "2025-10-17T03:33:23.917981Z",
          "zenith_sep_deg": 0.0,
          "hours_local": []
        }
      }
    },
    {
      "name": "Lacerta",
      "center": {
        "latitude": 48.0694782743494,
        "longitude": -99.24776278164649
      },
      "radiusMeters": 600000.0,
      "icrs": {
        "ra_deg": 340.0,
        "dec_deg": 48.069
      },
      "meta": {
        "visibilityTonight": {
          "visible": true,
          "max_alt_deg": 90.0,
          "max_alt_time_utc": "2025-10-17T03:33:23.917981Z",
          "zenith_sep_deg": 0.0,
          "hours_local": []
        }
      }
    },
    {
      "name": "Pegasus",
      "center": {
        "latitude": 22.628662441299102,
        "longitude": -95.40408307272952
      },
      "radiusMeters": 600000.0,
      "icrs": {
        "ra_deg": 343.844,
        "dec_deg": 22.629
      },
      "meta": {
        "visibilityTonight": {
          "visible": true,
          "max_alt_deg": 90.0,
          "max_alt_time_utc": "2025-10-17T03:33:23.917981Z",
          "zenith_sep_deg": 0.0,
          "hours_local": []
        }
      }
    },
    {
      "name": "Tucana",
      "center": {
        "latitude": -67.76386021625146,
        "longitude": -80.42928098891372
      },
      "radiusMeters": 600000.0,
      "icrs": {
        "ra_deg": 358.818,
        "dec_deg": -67.764
      },
      "meta": {
        "visibilityTonight": {
          "visible": true,
          "max_alt_deg": 90.0,
          "max_alt_time_utc": "2025-10-17T03:33:23.917981Z",
          "zenith_sep_deg": 0.0,
          "hours_local": []
        }
      }
    },
    {
      "name": "Pisces",
      "center": {
        "latitude": 11.073417405374855,
        "longitude": -73.4078585553231
      },
      "radiusMeters": 600000.0,
      "icrs": {
        "ra_deg": 5.84,
        "dec_deg": 11.073
      },
      "meta": {
        "visibilityTonight": {
          "visible": true,
          "max_alt_deg": 90.0,
          "max_alt_time_utc": "2025-10-17T03:33:23.917981Z",
          "zenith_sep_deg": 0.0,
          "hours_local": []
        }
      }
    },
    {
      "name": "Sculptor",
      "center": {
        "latitude": -32.456462483106705,
        "longitude": -72.60057226587676
      },
      "radiusMeters": 600000.0,
      "icrs": {
        "ra_deg": 6.647,
        "dec_deg": -32.456
      },
      "meta": {
        "visibilityTonight": {
          "visible": true,
          "max_alt_deg": 90.0,
          "max_alt_time_utc": "2025-10-17T03:33:23.917981Z",
          "zenith_sep_deg": 0.0,
          "hours_local": []
        }
      }
    },
    {
      "name": "Phoenix",
      "center": {
        "latitude": -47.71669241321577,
        "longitude": -71.82532182843406
      },
      "radiusMeters": 600000.0,
      "icrs": {
        "ra_deg": 7.422,
        "dec_deg": -47.717
      },
      "meta": {
        "visibilityTonight": {
          "visible": true,
          "max_alt_deg": 90.0,
          "max_alt_time_utc": "2025-10-17T03:33:23.917981Z",
          "zenith_sep_deg": 0.0,
          "hours_local": []
        }
      }
    },
    {
      "name": "Andromeda",
      "center": {
        "latitude": 41.75828441772241,
        "longitude": -70.6226319006229
      },
      "radiusMeters": 600000.0,
      "icrs": {
        "ra_deg": 8.625,
        "dec_deg": 41.758
      },
      "meta": {
        "visibilityTonight": {
          "visible": true,
          "max_alt_deg": 90.0,
          "max_alt_time_utc": "2025-10-17T03:33:23.917981Z",
          "zenith_sep_deg": 0.0,
          "hours_local": []
        }
      }
    },
    {
      "name": "Cassiopeia",
      "center": {
        "latitude": 64.14431285745282,
        "longitude": -63.02194749009729
      },
      "radiusMeters": 600000.0,
      "icrs": {
        "ra_deg": 16.226,
        "dec_deg": 64.144
      },
      "meta": {
        "visibilityTonight": {
          "visible": true,
          "max_alt_deg": 90.0,
          "max_alt_time_utc": "2025-10-17T03:33:23.917981Z",
          "zenith_sep_deg": 0.0,
          "hours_local": []
        }
      }
    },
    {
      "name": "Cetus",
      "center": {
        "latitude": -9.789478847430129,
        "longitude": -58.50699040247153
      },
      "radiusMeters": 600000.0,
      "icrs": {
        "ra_deg": 20.741,
        "dec_deg": -9.789
      },
      "meta": {
        "visibilityTonight": {
          "visible": true,
          "max_alt_deg": 90.0,
          "max_alt_time_utc": "2025-10-17T03:33:23.917981Z",
          "zenith_sep_deg": 0.0,
          "hours_local": []
        }
      }
    },
    {
      "name": "Triangulum",
      "center": {
        "latitude": 32.16783809218906,
        "longitude": -47.247762781646514
      },
      "radiusMeters": 600000.0,
      "icrs": {
        "ra_deg": 32.0,
        "dec_deg": 32.168
      },
      "meta": {
        "visibilityTonight": {
          "visible": true,
          "max_alt_deg": 90.0,
          "max_alt_time_utc": "2025-10-17T03:33:23.917981Z",
          "zenith_sep_deg": 0.0,
          "hours_local": []
        }
      }
    },
    {
      "name": "Hydrus",
      "center": {
        "latitude": -74.76466598158,
        "longitude": -43.433952676234384
      },
      "radiusMeters": 600000.0,
      "icrs": {
        "ra_deg": 35.814,
        "dec_deg": -74.765
      },
      "meta": {
        "visibilityTonight": {
          "visible": true,
          "max_alt_deg": 90.0,
          "max_alt_time_utc": "2025-10-17T03:33:23.917981Z",
          "zenith_sep_deg": 0.0,
          "hours_local": []
        }
      }
    },
    {
      "name": "Aries",
      "center": {
        "latitude": 20.120160714268305,
        "longitude": -39.247762781646514
      },
      "radiusMeters": 600000.0,
      "icrs": {
        "ra_deg": 40.0,
        "dec_deg": 20.12
      },
      "meta": {
        "visibilityTonight": {
          "visible": true,
          "max_alt_deg": 90.0,
          "max_alt_time_utc": "2025-10-17T03:33:23.917981Z",
          "zenith_sep_deg": 0.0,
          "hours_local": []
        }
      }
    },
    {
      "name": "Fornax",
      "center": {
        "latitude": -28.291180578908136,
        "longitude": -35.247762781646514
      },
      "radiusMeters": 600000.0,
      "icrs": {
        "ra_deg": 44.0,
        "dec_deg": -28.291
      },
      "meta": {
        "visibilityTonight": {
          "visible": true,
          "max_alt_deg": 90.0,
          "max_alt_time_utc": "2025-10-17T03:33:23.917981Z",
          "zenith_sep_deg": 0.0,
          "hours_local": []
        }
      }
    },
    {
      "name": "Horologium",
      "center": {
        "latitude": -53.34017471787428,
        "longitude": -26.98744958959665
      },
      "radiusMeters": 600000.0,
      "icrs": {
        "ra_deg": 52.26,
        "dec_deg": -53.34
      },
      "meta": {
        "visibilityTonight": {
          "visible": true,
          "max_alt_deg": 90.0,
          "max_alt_time_utc": "2025-10-17T03:33:23.917981Z",
          "zenith_sep_deg": 0.0,
          "hours_local": []
        }
      }
    },
    {
      "name": "Perseus",
      "center": {
        "latitude": 44.876363027497334,
        "longitude": -26.80205256082118
      },
      "radiusMeters": 600000.0,
      "icrs": {
        "ra_deg": 52.446,
        "dec_deg": 44.876
      },
      "meta": {
        "visibilityTonight": {
          "visible": true,
          "max_alt_deg": 90.0,
          "max_alt_time_utc": "2025-10-17T03:33:23.917981Z",
          "zenith_sep_deg": 0.0,
          "hours_local": []
        }
      }
    },
    {
      "name": "Eridanus",
      "center": {
        "latitude": -25.66392806622016,
        "longitude": -23.670742915877298
      },
      "radiusMeters": 600000.0,
      "icrs": {
        "ra_deg": 55.577,
        "dec_deg": -25.664
      },
      "meta": {
        "visibilityTonight": {
          "visible": true,
          "max_alt_deg": 90.0,
          "max_alt_time_utc": "2025-10-17T03:33:23.917981Z",
          "zenith_sep_deg": 0.0,
          "hours_local": []
        }
      }
    },
    {
      "name": "Reticulum",
      "center": {
        "latitude": -61.38511170986022,
        "longitude": -20.8076236219176
      },
      "radiusMeters": 600000.0,
      "icrs": {
        "ra_deg": 58.44,
        "dec_deg": -61.385
      },
      "meta": {
        "visibilityTonight": {
          "visible": true,
          "max_alt_deg": 90.0,
          "max_alt_time_utc": "2025-10-17T03:33:23.917981Z",
          "zenith_sep_deg": 0.0,
          "hours_local": []
        }
      }
    },
    {
      "name": "Taurus",
      "center": {
        "latitude": 18.529803655426846,
        "longitude": -10.311874705811562
      },
      "radiusMeters": 600000.0,
      "icrs": {
        "ra_deg": 68.936,
        "dec_deg": 18.53
      },
      "meta": {
        "visibilityTonight": {
          "visible": true,
          "max_alt_deg": 90.0,
          "max_alt_time_utc": "2025-10-17T03:33:23.917981Z",
          "zenith_sep_deg": 0.0,
          "hours_local": []
        }
      }
    },
    {
      "name": "Caelum",
      "center": {
        "latitude": -36.0,
        "longitude": -7.247762781646514
      },
      "radiusMeters": 600000.0,
      "icrs": {
        "ra_deg": 72.0,
        "dec_deg": -36.0
      },
      "meta": {
        "visibilityTonight": {
          "visible": true,
          "max_alt_deg": 90.0,
          "max_alt_time_utc": "2025-10-17T03:33:23.917981Z",
          "zenith_sep_deg": 0.0,
          "hours_local": []
        }
      }
    },
    {
      "name": "Dorado",
      "center": {
        "latitude": -61.04691760135666,
        "longitude": -4.7731212499165
      },
      "radiusMeters": 600000.0,
      "icrs": {
        "ra_deg": 74.475,
        "dec_deg": -61.047
      },
      "meta": {
        "visibilityTonight": {
          "visible": true,
          "max_alt_deg": 90.0,
          "max_alt_time_utc": "2025-10-17T03:33:23.917981Z",
          "zenith_sep_deg": 0.0,
          "hours_local": []
        }
      }
    },
    {
      "name": "Orion",
      "center": {
        "latitude": 4.031470597757756,
        "longitude": 3.1085811800691374
      },
      "radiusMeters": 600000.0,
      "icrs": {
        "ra_deg": 82.356,
        "dec_deg": 4.031
      },
      "meta": {
        "visibilityTonight": {
          "visible": true,
          "max_alt_deg": 90.0,
          "max_alt_time_utc": "2025-10-17T03:33:23.917981Z",
          "zenith_sep_deg": 0.0,
          "hours_local": []
        }
      }
    },
    {
      "name": "Mensa",
      "center": {
        "latitude": -77.73290394155632,
        "longitude": 4.752237218353486
      },
      "radiusMeters": 600000.0,
      "icrs": {
        "ra_deg": 84.0,
        "dec_deg": -77.733
      },
      "meta": {
        "visibilityTonight": {
          "visible": true,
          "max_alt_deg": 90.0,
          "max_alt_time_utc": "2025-10-17T03:33:23.917981Z",
          "zenith_sep_deg": 0.0,
          "hours_local": []
        }
      }
    },
    {
      "name": "Lepus",
      "center": {
        "latitude": -20.04495350306864,
        "longitude": 4.752237218353486
      },
      "radiusMeters": 600000.0,
      "icrs": {
        "ra_deg": 84.0,
        "dec_deg": -20.045
      },
      "meta": {
        "visibilityTonight": {
          "visible": true,
          "max_alt_deg": 90.0,
          "max_alt_time_utc": "2025-10-17T03:33:23.917981Z",
          "zenith_sep_deg": 0.0,
          "hours_local": []
        }
      }
    },
    {
      "name": "Pictor",
      "center": {
        "latitude": -53.98849395497563,
        "longitude": 5.710861868435217
      },
      "radiusMeters": 600000.0,
      "icrs": {
        "ra_deg": 84.959,
        "dec_deg": -53.988
      },
      "meta": {
        "visibilityTonight": {
          "visible": true,
          "max_alt_deg": 90.0,
          "max_alt_time_utc": "2025-10-17T03:33:23.917981Z",
          "zenith_sep_deg": 0.0,
          "hours_local": []
        }
      }
    },
    {
      "name": "Columba",
      "center": {
        "latitude": -36.94906968567858,
        "longitude": 7.049829955983483
      },
      "radiusMeters": 600000.0,
      "icrs": {
        "ra_deg": 86.298,
        "dec_deg": -36.949
      },
      "meta": {
        "visibilityTonight": {
          "visible": true,
          "max_alt_deg": 90.0,
          "max_alt_time_utc": "2025-10-17T03:33:23.917981Z",
          "zenith_sep_deg": 0.0,
          "hours_local": []
        }
      }
    },
    {
      "name": "Auriga",
      "center": {
        "latitude": 42.64235318018317,
        "longitude": 10.847484066721535
      },
      "radiusMeters": 600000.0,
      "icrs": {
        "ra_deg": 90.095,
        "dec_deg": 42.642
      },
      "meta": {
        "visibilityTonight": {
          "visible": true,
          "max_alt_deg": 90.0,
          "max_alt_time_utc": "2025-10-17T03:33:23.917981Z",
          "zenith_sep_deg": 0.0,
          "hours_local": []
        }
      }
    },
    {
      "name": "Camelopardalis",
      "center": {
        "latitude": 75.71236718531524,
        "longitude": 13.704500546189678
      },
      "radiusMeters": 600000.0,
      "icrs": {
        "ra_deg": 92.952,
        "dec_deg": 75.712
      },
      "meta": {
        "visibilityTonight": {
          "visible": true,
          "max_alt_deg": 90.0,
          "max_alt_time_utc": "2025-10-17T03:33:23.917981Z",
          "zenith_sep_deg": 0.0,
          "hours_local": []
        }
      }
    },
    {
      "name": "Canis Major",
      "center": {
        "latitude": -24.05196585783449,
        "longitude": 20.752237218353486
      },
      "radiusMeters": 600000.0,
      "icrs": {
        "ra_deg": 100.0,
        "dec_deg": -24.052
      },
      "meta": {
        "visibilityTonight": {
          "visible": true,
          "max_alt_deg": 90.0,
          "max_alt_time_utc": "2025-10-17T03:33:23.917981Z",
          "zenith_sep_deg": 0.0,
          "hours_local": []
        }
      }
    },
    {
      "name": "Monoceros",
      "center": {
        "latitude": -2.0269815981411488,
        "longitude": 24.72282725456793
      },
      "radiusMeters": 600000.0,
      "icrs": {
        "ra_deg": 103.971,
        "dec_deg": -2.027
      },
      "meta": {
        "visibilityTonight": {
          "visible": true,
          "max_alt_deg": 90.0,
          "max_alt_time_utc": "2025-10-17T03:33:23.917981Z",
          "zenith_sep_deg": 0.0,
          "hours_local": []
        }
      }
    },
    {
      "name": "Gemini",
      "center": {
        "latitude": 25.080087386328724,
        "longitude": 30.007122019714103
      },
      "radiusMeters": 600000.0,
      "icrs": {
        "ra_deg": 109.255,
        "dec_deg": 25.08
      },
      "meta": {
        "visibilityTonight": {
          "visible": true,
          "max_alt_deg": 90.0,
          "max_alt_time_utc": "2025-10-17T03:33:23.917981Z",
          "zenith_sep_deg": 0.0,
          "hours_local": []
        }
      }
    },
    {
      "name": "Puppis",
      "center": {
        "latitude": -35.31142478126854,
        "longitude": 33.82992784178899
      },
      "radiusMeters": 600000.0,
      "icrs": {
        "ra_deg": 113.078,
        "dec_deg": -35.311
      },
      "meta": {
        "visibilityTonight": {
          "visible": true,
          "max_alt_deg": 90.0,
          "max_alt_time_utc": "2025-10-17T03:33:23.917981Z",
          "zenith_sep_deg": 0.0,
          "hours_local": []
        }
      }
    },
    {
      "name": "Volans",
      "center": {
        "latitude": -72.20472995989934,
        "longitude": 36.752237218353486
      },
      "radiusMeters": 600000.0,
      "icrs": {
        "ra_deg": 116.0,
        "dec_deg": -72.205
      },
      "meta": {
        "visibilityTonight": {
          "visible": true,
          "max_alt_deg": 90.0,
          "max_alt_time_utc": "2025-10-17T03:33:23.917981Z",
          "zenith_sep_deg": 0.0,
          "hours_local": []
        }
      }
    },
    {
      "name": "Canis Minor",
      "center": {
        "latitude": 4.009735770097598,
        "longitude": 36.752237218353486
      },
      "radiusMeters": 600000.0,
      "icrs": {
        "ra_deg": 116.0,
        "dec_deg": 4.01
      },
      "meta": {
        "visibilityTonight": {
          "visible": true,
          "max_alt_deg": 90.0,
          "max_alt_time_utc": "2025-10-17T03:33:23.917981Z",
          "zenith_sep_deg": 0.0,
          "hours_local": []
        }
      }
    },
    {
      "name": "Lynx",
      "center": {
        "latitude": 49.37487657030485,
        "longitude": 42.60234820207987
      },
      "radiusMeters": 600000.0,
      "icrs": {
        "ra_deg": 121.85,
        "dec_deg": 49.375
      },
      "meta": {
        "visibilityTonight": {
          "visible": true,
          "max_alt_deg": 90.0,
          "max_alt_time_utc": "2025-10-17T03:33:23.917981Z",
          "zenith_sep_deg": 0.0,
          "hours_local": []
        }
      }
    },
    {
      "name": "Cancer",
      "center": {
        "latitude": 19.630332282382398,
        "longitude": 51.38086187871116
      },
      "radiusMeters": 600000.0,
      "icrs": {
        "ra_deg": 130.629,
        "dec_deg": 19.63
      },
      "meta": {
        "visibilityTonight": {
          "visible": true,
          "max_alt_deg": 90.0,
          "max_alt_time_utc": "2025-10-17T03:33:23.917981Z",
          "zenith_sep_deg": 0.0,
          "hours_local": []
        }
      }
    },
    {
      "name": "Pyxis",
      "center": {
        "latitude": -28.057964295257996,
        "longitude": 52.752237218353486
      },
      "radiusMeters": 600000.0,
      "icrs": {
        "ra_deg": 132.0,
        "dec_deg": -28.058
      },
      "meta": {
        "visibilityTonight": {
          "visible": true,
          "max_alt_deg": 90.0,
          "max_alt_time_utc": "2025-10-17T03:33:23.917981Z",
          "zenith_sep_deg": 0.0,
          "hours_local": []
        }
      }
    },
    {
      "name": "Carina",
      "center": {
        "latitude": -65.88363751591707,
        "longitude": 54.073549332354474
      },
      "radiusMeters": 600000.0,
      "icrs": {
        "ra_deg": 133.321,
        "dec_deg": -65.884
      },
      "meta": {
        "visibilityTonight": {
          "visible": true,
          "max_alt_deg": 90.0,
          "max_alt_time_utc": "2025-10-17T03:33:23.917981Z",
          "zenith_sep_deg": 0.0,
          "hours_local": []
        }
      }
    },
    {
      "name": "Vela",
      "center": {
        "latitude": -49.98900697827747,
        "longitude": 63.40932014719783
      },
      "radiusMeters": 600000.0,
      "icrs": {
        "ra_deg": 142.657,
        "dec_deg": -49.989
      },
      "meta": {
        "visibilityTonight": {
          "visible": true,
          "max_alt_deg": 90.0,
          "max_alt_time_utc": "2025-10-17T03:33:23.917981Z",
          "zenith_sep_deg": 0.0,
          "hours_local": []
        }
      }
    },
    {
      "name": "Antlia",
      "center": {
        "latitude": -36.17752252650312,
        "longitude": 72.75223721835346
      },
      "radiusMeters": 600000.0,
      "icrs": {
        "ra_deg": 152.0,
        "dec_deg": -36.178
      },
      "meta": {
        "visibilityTonight": {
          "visible": true,
          "max_alt_deg": 90.0,
          "max_alt_time_utc": "2025-10-17T03:33:23.917981Z",
          "zenith_sep_deg": 0.0,
          "hours_local": []
        }
      }
    },
    {
      "name": "Hydra",
      "center": {
        "latitude": -18.67134494008078,
        "longitude": 75.28055320838195
      },
      "radiusMeters": 600000.0,
      "icrs": {
        "ra_deg": 154.528,
        "dec_deg": -18.671
      },
      "meta": {
        "visibilityTonight": {
          "visible": true,
          "max_alt_deg": 90.0,
          "max_alt_time_utc": "2025-10-17T03:33:23.917981Z",
          "zenith_sep_deg": 0.0,
          "hours_local": []
        }
      }
    },
    {
      "name": "Sextans",
      "center": {
        "latitude": -4.009735770097598,
        "longitude": 76.75223721835346
      },
      "radiusMeters": 600000.0,
      "icrs": {
        "ra_deg": 156.0,
        "dec_deg": -4.01
      },
      "meta": {
        "visibilityTonight": {
          "visible": true,
          "max_alt_deg": 90.0,
          "max_alt_time_utc": "2025-10-17T03:33:23.917981Z",
          "zenith_sep_deg": 0.0,
          "hours_local": []
        }
      }
    },
    {
      "name": "Leo Minor",
      "center": {
        "latitude": 32.06271191125027,
        "longitude": 76.9273016678444
      },
      "radiusMeters": 600000.0,
      "icrs": {
        "ra_deg": 156.175,
        "dec_deg": 32.063
      },
      "meta": {
        "visibilityTonight": {
          "visible": true,
          "max_alt_deg": 90.0,
          "max_alt_time_utc": "2025-10-17T03:33:23.917981Z",
          "zenith_sep_deg": 0.0,
          "hours_local": []
        }
      }
    },
    {
      "name": "Leo",
      "center": {
        "latitude": 16.300223425409577,
        "longitude": 79.24709557683923
      },
      "radiusMeters": 600000.0,
      "icrs": {
        "ra_deg": 158.495,
        "dec_deg": 16.3
      },
      "meta": {
        "visibilityTonight": {
          "visible": true,
          "max_alt_deg": 90.0,
          "max_alt_time_utc": "2025-10-17T03:33:23.917981Z",
          "zenith_sep_deg": 0.0,
          "hours_local": []
        }
      }
    },
    {
      "name": "Chamaleon",
      "center": {
        "latitude": -81.10309889917112,
        "longitude": 84.75223721835346
      },
      "radiusMeters": 600000.0,
      "icrs": {
        "ra_deg": 164.0,
        "dec_deg": -81.103
      },
      "meta": {
        "visibilityTonight": {
          "visible": true,
          "max_alt_deg": 90.0,
          "max_alt_time_utc": "2025-10-17T03:33:23.917981Z",
          "zenith_sep_deg": 0.0,
          "hours_local": []
        }
      }
    },
    {
      "name": "Ursa Major",
      "center": {
        "latitude": 57.925362948044565,
        "longitude": 85.88877776386613
      },
      "radiusMeters": 600000.0,
      "icrs": {
        "ra_deg": 165.137,
        "dec_deg": 57.925
      },
      "meta": {
        "visibilityTonight": {
          "visible": true,
          "max_alt_deg": 90.0,
          "max_alt_time_utc": "2025-10-17T03:33:23.917981Z",
          "zenith_sep_deg": 0.0,
          "hours_local": []
        }
      }
    },
    {
      "name": "Crater",
      "center": {
        "latitude": -16.03706374099387,
        "longitude": 92.75223721835346
      },
      "radiusMeters": 600000.0,
      "icrs": {
        "ra_deg": 172.0,
        "dec_deg": -16.037
      },
      "meta": {
        "visibilityTonight": {
          "visible": true,
          "max_alt_deg": 90.0,
          "max_alt_time_utc": "2025-10-17T03:33:23.917981Z",
          "zenith_sep_deg": 0.0,
          "hours_local": []
        }
      }
    },
    {
      "name": "Corvus",
      "center": {
        "latitude": -18.70273421795923,
        "longitude": 107.46189079478216
      },
      "radiusMeters": 600000.0,
      "icrs": {
        "ra_deg": 186.71,
        "dec_deg": -18.703
      },
      "meta": {
        "visibilityTonight": {
          "visible": true,
          "max_alt_deg": 90.0,
          "max_alt_time_utc": "2025-10-17T03:33:23.917981Z",
          "zenith_sep_deg": 0.0,
          "hours_local": []
        }
      }
    },
    {
      "name": "Musca",
      "center": {
        "latitude": -72.20472995989934,
        "longitude": 108.75223721835346
      },
      "radiusMeters": 600000.0,
      "icrs": {
        "ra_deg": 188.0,
        "dec_deg": -72.205
      },
      "meta": {
        "visibilityTonight": {
          "visible": true,
          "max_alt_deg": 90.0,
          "max_alt_time_utc": "2025-10-17T03:33:23.917981Z",
          "zenith_sep_deg": 0.0,
          "hours_local": []
        }
      }
    },
    {
      "name": "Crux",
      "center": {
        "latitude": -60.060472230968024,
        "longitude": 108.75223721835346
      },
      "radiusMeters": 600000.0,
      "icrs": {
        "ra_deg": 188.0,
        "dec_deg": -60.06
      },
      "meta": {
        "visibilityTonight": {
          "visible": true,
          "max_alt_deg": 90.0,
          "max_alt_time_utc": "2025-10-17T03:33:23.917981Z",
          "zenith_sep_deg": 0.0,
          "hours_local": []
        }
      }
    },
    {
      "name": "Coma Berenices",
      "center": {
        "latitude": 21.84378969402826,
        "longitude": 111.7002939916577
      },
      "radiusMeters": 600000.0,
      "icrs": {
        "ra_deg": 190.948,
        "dec_deg": 21.844
      },
      "meta": {
        "visibilityTonight": {
          "visible": true,
          "max_alt_deg": 90.0,
          "max_alt_time_utc": "2025-10-17T03:33:23.917981Z",
          "zenith_sep_deg": 0.0,
          "hours_local": []
        }
      }
    },
    {
      "name": "Canes Venatici",
      "center": {
        "latitude": 40.289444735714866,
        "longitude": 117.03498368769118
      },
      "radiusMeters": 600000.0,
      "icrs": {
        "ra_deg": 196.283,
        "dec_deg": 40.289
      },
      "meta": {
        "visibilityTonight": {
          "visible": true,
          "max_alt_deg": 90.0,
          "max_alt_time_utc": "2025-10-17T03:33:23.917981Z",
          "zenith_sep_deg": 0.0,
          "hours_local": []
        }
      }
    },
    {
      "name": "Centaurus",
      "center": {
        "latitude": -47.85368582154014,
        "longitude": 117.81626036231017
      },
      "radiusMeters": 600000.0,
      "icrs": {
        "ra_deg": 197.064,
        "dec_deg": -47.854
      },
      "meta": {
        "visibilityTonight": {
          "visible": true,
          "max_alt_deg": 90.0,
          "max_alt_time_utc": "2025-10-17T03:33:23.917981Z",
          "zenith_sep_deg": 0.0,
          "hours_local": []
        }
      }
    },
    {
      "name": "Virgo",
      "center": {
        "latitude": -2.2802828800114225,
        "longitude": 118.50545690997347
      },
      "radiusMeters": 600000.0,
      "icrs": {
        "ra_deg": 197.753,
        "dec_deg": -2.28
      },
      "meta": {
        "visibilityTonight": {
          "visible": true,
          "max_alt_deg": 90.0,
          "max_alt_time_utc": "2025-10-17T03:33:23.917981Z",
          "zenith_sep_deg": 0.0,
          "hours_local": []
        }
      }
    },
    {
      "name": "Bo\u00f6tes",
      "center": {
        "latitude": 27.946531577471653,
        "longitude": 139.57586751532585
      },
      "radiusMeters": 600000.0,
      "icrs": {
        "ra_deg": 218.824,
        "dec_deg": 27.947
      },
      "meta": {
        "visibilityTonight": {
          "visible": true,
          "max_alt_deg": 90.0,
          "max_alt_time_utc": "2025-10-17T03:33:23.917981Z",
          "zenith_sep_deg": 0.0,
          "hours_local": []
        }
      }
    },
    {
      "name": "Circinus",
      "center": {
        "latitude": -58.72184676715823,
        "longitude": 147.62417932703568
      },
      "radiusMeters": 600000.0,
      "icrs": {
        "ra_deg": 226.872,
        "dec_deg": -58.722
      },
      "meta": {
        "visibilityTonight": {
          "visible": true,
          "max_alt_deg": 90.0,
          "max_alt_time_utc": "2025-10-17T03:33:23.917981Z",
          "zenith_sep_deg": 0.0,
          "hours_local": []
        }
      }
    },
    {
      "name": "Libra",
      "center": {
        "latitude": -16.156454823145573,
        "longitude": 148.848860817866
      },
      "radiusMeters": 600000.0,
      "icrs": {
        "ra_deg": 228.097,
        "dec_deg": -16.156
      },
      "meta": {
        "visibilityTonight": {
          "visible": true,
          "max_alt_deg": 90.0,
          "max_alt_time_utc": "2025-10-17T03:33:23.917981Z",
          "zenith_sep_deg": 0.0,
          "hours_local": []
        }
      }
    },
    {
      "name": "Ursa Minor",
      "center": {
        "latitude": 76.64394220009358,
        "longitude": 149.3406526389549
      },
      "radiusMeters": 600000.0,
      "icrs": {
        "ra_deg": 228.588,
        "dec_deg": 76.644
      },
      "meta": {
        "visibilityTonight": {
          "visible": true,
          "max_alt_deg": 90.0,
          "max_alt_time_utc": "2025-10-17T03:33:23.917981Z",
          "zenith_sep_deg": 0.0,
          "hours_local": []
        }
      }
    },
    {
      "name": "Lupus",
      "center": {
        "latitude": -41.40789391391216,
        "longitude": 152.16770509086592
      },
      "radiusMeters": 600000.0,
      "icrs": {
        "ra_deg": 231.415,
        "dec_deg": -41.408
      },
      "meta": {
        "visibilityTonight": {
          "visible": true,
          "max_alt_deg": 90.0,
          "max_alt_time_utc": "2025-10-17T03:33:23.917981Z",
          "zenith_sep_deg": 0.0,
          "hours_local": []
        }
      }
    },
    {
      "name": "Corona Borealis",
      "center": {
        "latitude": 32.06283223102342,
        "longitude": 156.75223721835346
      },
      "radiusMeters": 600000.0,
      "icrs": {
        "ra_deg": 236.0,
        "dec_deg": 32.063
      },
      "meta": {
        "visibilityTonight": {
          "visible": true,
          "max_alt_deg": 90.0,
          "max_alt_time_utc": "2025-10-17T03:33:23.917981Z",
          "zenith_sep_deg": 0.0,
          "hours_local": []
        }
      }
    },
    {
      "name": "Triangulum Australe",
      "center": {
        "latitude": -64.14664707868641,
        "longitude": 160.75223721835346
      },
      "radiusMeters": 600000.0,
      "icrs": {
        "ra_deg": 240.0,
        "dec_deg": -64.147
      },
      "meta": {
        "visibilityTonight": {
          "visible": true,
          "max_alt_deg": 90.0,
          "max_alt_time_utc": "2025-10-17T03:33:23.917981Z",
          "zenith_sep_deg": 0.0,
          "hours_local": []
        }
      }
    },
    {
      "name": "Apus",
      "center": {
        "latitude": -76.5841796062668,
        "longitude": 162.09704306875915
      },
      "radiusMeters": 600000.0,
      "icrs": {
        "ra_deg": 241.345,
        "dec_deg": -76.584
      },
      "meta": {
        "visibilityTonight": {
          "visible": true,
          "max_alt_deg": 90.0,
          "max_alt_time_utc": "2025-10-17T03:33:23.917981Z",
          "zenith_sep_deg": 0.0,
          "hours_local": []
        }
      }
    },
    {
      "name": "Norma",
      "center": {
        "latitude": -52.06777445816242,
        "longitude": 164.7522372183534
      },
      "radiusMeters": 600000.0,
      "icrs": {
        "ra_deg": 244.0,
        "dec_deg": -52.068
      },
      "meta": {
        "visibilityTonight": {
          "visible": true,
          "max_alt_deg": 90.0,
          "max_alt_time_utc": "2025-10-17T03:33:23.917981Z",
          "zenith_sep_deg": 0.0,
          "hours_local": []
        }
      }
    },
    {
      "name": "Serpens",
      "center": {
        "latitude": 6.2958310000092785,
        "longitude": 168.75800242417728
      },
      "radiusMeters": 600000.0,
      "icrs": {
        "ra_deg": 248.006,
        "dec_deg": 6.296
      },
      "meta": {
        "visibilityTonight": {
          "visible": true,
          "max_alt_deg": 90.0,
          "max_alt_time_utc": "2025-10-17T03:33:23.917981Z",
          "zenith_sep_deg": 0.0,
          "hours_local": []
        }
      }
    },
    {
      "name": "Draco",
      "center": {
        "latitude": 70.8528544101679,
        "longitude": 171.97333791764936
      },
      "radiusMeters": 600000.0,
      "icrs": {
        "ra_deg": 251.221,
        "dec_deg": 70.853
      },
      "meta": {
        "visibilityTonight": {
          "visible": true,
          "max_alt_deg": 90.0,
          "max_alt_time_utc": "2025-10-17T03:33:23.917981Z",
          "zenith_sep_deg": 0.0,
          "hours_local": []
        }
      }
    },
    {
      "name": "Scorpius",
      "center": {
        "latitude": -34.575618350214,
        "longitude": 174.2178659507602
      },
      "radiusMeters": 600000.0,
      "icrs": {
        "ra_deg": 253.466,
        "dec_deg": -34.576
      },
      "meta": {
        "visibilityTonight": {
          "visible": true,
          "max_alt_deg": 90.0,
          "max_alt_time_utc": "2025-10-17T03:33:23.917981Z",
          "zenith_sep_deg": 0.0,
          "hours_local": []
        }
      }
    },
    {
      "name": "Ophiucus",
      "center": {
        "latitude": -6.461998583015874,
        "longitude": 179.45578424971904
      },
      "radiusMeters": 600000.0,
      "icrs": {
        "ra_deg": 258.704,
        "dec_deg": -6.462
      },
      "meta": {
        "visibilityTonight": {
          "visible": true,
          "max_alt_deg": 90.0,
          "max_alt_time_utc": "2025-10-17T03:33:23.917981Z",
          "zenith_sep_deg": 0.0,
          "hours_local": []
        }
      }
    }
  ],
  "starDots": {
    "bright": [
      {
        "latitude": 7.0,
        "longitude": -72.0
      },
      {
        "latitude": 21.0,
        "longitude": -33.0
      },
      {
        "latitude": -5.0,
        "longitude": 14.0
      }
    ]
  },
  "asterisms": [
    {
      "name": "Summer Triangle",
      "parent": "Aquila/Lyra/Cygnus",
      "kind": "triangle",
      "center": {
        "latitude": 31.684659444016116,
        "longitude": -143.7488436798285
      },
      "icrs": {
        "ra_deg": 295.499,
        "dec_deg": 31.685
      },
      "meta": {
        "visibilityTonight": {
          "visible": true,
          "hours_local": [],
          "max_alt_deg": 90.0,
          "max_alt_time_utc": "2025-10-17T03:33:23.917981Z",
          "zenith_sep_deg": 0.0
        }
      }
    },
    {
      "name": "Northern Cross",
      "parent": "Cygnus",
      "kind": "line",
      "center": {
        "latitude": 40.08011866063746,
        "longitude": -136.86234412059594
      },
      "icrs": {
        "ra_deg": 302.385,
        "dec_deg": 40.08
      },
      "meta": {
        "visibilityTonight": {
          "visible": true,
          "hours_local": [],
          "max_alt_deg": 90.0,
          "max_alt_time_utc": "2025-10-17T03:33:23.917981Z",
          "zenith_sep_deg": 0.0
        }
      }
    },
    {
      "name": "Pleiades",
      "parent": "Taurus",
      "kind": "cluster",
      "center": {
        "latitude": 24.101755341015124,
        "longitude": -22.390677575453907
      },
      "icrs": {
        "ra_deg": 56.857,
        "dec_deg": 24.102
      },
      "meta": {
        "visibilityTonight": {
          "visible": true,
          "hours_local": [],
          "max_alt_deg": 90.0,
          "max_alt_time_utc": "2025-10-17T03:33:23.917981Z",
          "zenith_sep_deg": 0.0
        }
      }
    },
    {
      "name": "Orion's Belt",
      "parent": "Orion",
      "kind": "line",
      "center": {
        "latitude": -1.148008053153754,
        "longitude": 4.833630130751629
      },
      "icrs": {
        "ra_deg": 84.081,
        "dec_deg": -1.148
      },
      "meta": {
        "visibilityTonight": {
          "visible": true,
          "hours_local": [],
          "max_alt_deg": 90.0,
          "max_alt_time_utc": "2025-10-17T03:33:23.917981Z",
          "zenith_sep_deg": 0.0
        }
      }
    },
    {
      "name": "Big Dipper",
      "parent": "Ursa Major",
      "kind": "line",
      "center": {
        "latitude": 56.51222598221586,
        "longitude": 106.75154514374577
      },
      "icrs": {
        "ra_deg": 185.999,
        "dec_deg": 56.512
      },
      "meta": {
        "visibilityTonight": {
          "visible": true,
          "hours_local": [],
          "max_alt_deg": 90.0,
          "max_alt_time_utc": "2025-10-17T03:33:23.917981Z",
          "zenith_sep_deg": 0.0
        }
      }
    }
  ]
}